slapping/__init__.py
slapping/py.typed
slapping/slap_that_like_button.py
slapping-0.0.10.dist-info/LICENSE
slapping-0.0.10.dist-info/METADATA
slapping-0.0.10.dist-info/WHEEL
slapping-0.0.10.dist-info/top_level.txt
slapping-0.0.10.dist-info/RECORD
